nonebot_plugin_gocqhttpQQ/__init__.py
nonebot_plugin_gocqhttpQQ/exceptions.py
nonebot_plugin_gocqhttpQQ/external_proxy.py
nonebot_plugin_gocqhttpQQ/log.py
nonebot_plugin_gocqhttpQQ/plugin.py
nonebot_plugin_gocqhttpQQ/plugin_config.py
nonebot_plugin_gocqhttpQQ/process/__init__.py
nonebot_plugin_gocqhttpQQ/process/config-template.yml
nonebot_plugin_gocqhttpQQ/process/config.py
nonebot_plugin_gocqhttpQQ/process/device/__init__.py
nonebot_plugin_gocqhttpQQ/process/device/android_builds.csv
nonebot_plugin_gocqhttpQQ/process/device/android_devices.csv
nonebot_plugin_gocqhttpQQ/process/device/data_source.py
nonebot_plugin_gocqhttpQQ/process/device/generator.py
nonebot_plugin_gocqhttpQQ/process/device/models.py
nonebot_plugin_gocqhttpQQ/process/download.py
nonebot_plugin_gocqhttpQQ/process/manager.py
nonebot_plugin_gocqhttpQQ/process/models.py
nonebot_plugin_gocqhttpQQ/process/platform.py
nonebot_plugin_gocqhttpQQ/process/process.py
nonebot_plugin_gocqhttpQQ/web/.gitignore
nonebot_plugin_gocqhttpQQ/web/__init__.py
nonebot_plugin_gocqhttpQQ/web/api.py
nonebot_plugin_gocqhttpQQ/web/dist/css/290.7fbd3c05.css
nonebot_plugin_gocqhttpQQ/web/dist/css/477.e40964b0.css
nonebot_plugin_gocqhttpQQ/web/dist/css/666.d23b86f9.css
nonebot_plugin_gocqhttpQQ/web/dist/css/679.e40964b0.css
nonebot_plugin_gocqhttpQQ/web/dist/css/app.bd26fad1.css
nonebot_plugin_gocqhttpQQ/web/dist/editor.worker.afbd84bf87ff32f64c63d43e1a5dde9a.js
nonebot_plugin_gocqhttpQQ/web/dist/favicon.ico
nonebot_plugin_gocqhttpQQ/web/dist/fonts/codicon.4a477f66.ttf
nonebot_plugin_gocqhttpQQ/web/dist/fonts/flUhRq6tzZclQEJ-Vdg-IuiaDsNa.4d73cb90.woff
nonebot_plugin_gocqhttpQQ/web/dist/fonts/flUhRq6tzZclQEJ-Vdg-IuiaDsNcIhQ8tQ.c5371cfb.woff2
nonebot_plugin_gocqhttpQQ/web/dist/fonts/KFOkCnqEu92Fr1MmgVxIIzQ.68bb21d0.woff
nonebot_plugin_gocqhttpQQ/web/dist/fonts/KFOlCnqEu92Fr1MmEU9fBBc-.48af7707.woff
nonebot_plugin_gocqhttpQQ/web/dist/fonts/KFOlCnqEu92Fr1MmSU5fBBc-.c2f7ab22.woff
nonebot_plugin_gocqhttpqq-0.0.2.dist-info/LICENSE
nonebot_plugin_gocqhttpqq-0.0.2.dist-info/METADATA
nonebot_plugin_gocqhttpqq-0.0.2.dist-info/WHEEL
nonebot_plugin_gocqhttpqq-0.0.2.dist-info/RECORD
