Metadata-Version: 2.1
Name: nonebot-plugin-gocqhttpQQ
Version: 0.0.2
Summary: 修改了一些代码.
Home-page: https://github.com/2027839379/nonebot_plugin_gocqhttpQQ
License: AGPL-3.0
Author: Mix
Author-email: mnixry@users.noreply.github.com
Requires-Python: >=3.8,<4.0
Classifier: License :: OSI Approved :: GNU Affero General Public License v3
Classifier: Programming Language :: Python :: 3
Classifier: Programming Language :: Python :: 3.8
Classifier: Programming Language :: Python :: 3.9
Classifier: Programming Language :: Python :: 3.10
Classifier: Programming Language :: Python :: 3.11
Classifier: Programming Language :: Python :: 3.12
Provides-Extra: proxy
Requires-Dist: chevron (>=0.14.0,<0.15.0)
Requires-Dist: httpx (>=0.20.0)
Requires-Dist: nonebot-adapter-onebot (>=2.0.0,<3.0.0)
Requires-Dist: nonebot2[fastapi] (>=2.0.0,<3.0.0)
Requires-Dist: proxy.py (>=2.4.3,<3.0.0) ; extra == "proxy"
Requires-Dist: psutil (>=5.9.0,<6.0.0)
Requires-Dist: py-cpuinfo (>=8,<10)
Project-URL: Repository, https://github.com/2027839379/nonebot_plugin_gocqhttpQQ
